[
  {
    "category": "Закуски",
    "name": "хлеб с копчёным маслом и лардом с травами",
    "content": [
      { "label": "хлеб пшеничный и мультизлаковый тартин", "full": "хлеб пшеничный и мультизлаковый тартин" },
      { "label": "бородинский хлеб", "full": "бородинский хлеб" },
      { "label": "лард", "full": "лард (свиное сало, петрушка, укроп, мята)" }
    ],
    "sauce": [
      { "label": "копченое сливочное масло", "full": "копченое сливочное масло" },
      { "label": "чернила каракатицы", "full": "чернила каракатицы" }
    ]
  },
  {
    "category": "Закуски",
    "name": "картофельные пышки со сметаной и щучьей икрой",
    "taste": ["острый", "пряный"],
    "content": [
      { "label": "тесто пончиковое", "full": "тесто пончиковое (мука пшеничная, картофель, дрожжи, молоко, яйцо куриное, соль, сливочное масло)" },
      { "label": "щучья икра", "full": "щучья икра" },
      { "label": "лук сибулет", "full": "лук сибулет" },
      { "label": "пыль из шалота", "full": "пыль из шалота" }
    ],
    "sauce": [
      { "label": "сметана копченая", "full": "сметана копченая" }
    ]
  },
  {
    "category": "Закуски",
    "name": "паштет из куриной печени с чёрной смородиной",
    "content": [
      { "label": "печень", "full": "печень" },
      { "label": "бульон куриный", "full": "бульон куриный" },
      { "label": "вино красное", "full": "вино красное" },
      { "label": "перец", "full": "перец" },
      { "label": "соль", "full": "соль" },
      { "label": "масло сливочное", "full": "масло сливочное" },
      { "label": "яйцо куриное", "full": "яйцо куриное" },
      { "label": "чеснок", "full": "чеснок" },
      { "label": "лук белый", "full": "лук белый" },
      { "label": "коньяк армянский", "full": "коньяк армянский" },
      { "label": "бриошь", "full": "бриошь" },
      { "label": "кранч орегано", "full": "кранч орегано (грецкий орех, мука пшеничная, сливочное и оливковое масло, орегано сухой, сахар, соль)" }
    ],
    "sauce": [
      { "label": "варенье из черной смородины с мятой", "full": "варенье из черной смородины с мятой" }
    ]
  },
  {
    "category": "Закуски",
    "name": "тартар из говядины с вяленой свеклой, пекорино и картофелем фри",
    "content": [
      { "label": "говядина зернового откорма", "full": "говядина зернового откорма (бавет — вырезка из нижней части живота)" },
      { "label": "вяленая свекла", "full": "вяленая свекла" },
      { "label": "тертый пекорино", "full": "тертый пекорино" },
      { "label": "картофель фри или бриошь", "full": "картофель фри или бриошь" }
    ],
    "sauce": [
      { "label": "каперсы", "full": "каперсы" },
      { "label": "лимонный сок", "full": "лимонный сок" },
      { "label": "соус для свеклы", "full": "соус для восстановления свеклы (вустершир, горчица, шрирача, оливковое масло)" }
    ]
  },
  {
    "category": "Закуски",
    "name": "холодец из утиной ножки с кремом из васаби и бородинским хлебом",
    "content": [
      { "label": "бульон на холодец", "full": "бульон на холодец (утка, курица, соевый соус, бадьян, корица)" },
      { "label": "бородинский хлеб", "full": "бородинский хлеб" },
      { "label": "битый огурец", "full": "битый огурец (маринад из соуса кимчи, соков апельсина и лайма, соевого соуса)" },
      { "label": "васаби кидзами", "full": "васаби кидзами (мелко нарезанный стебель)" }
    ],
    "sauce": [
      { "label": "васаби крем", "full": "васаби крем (белок, паста васаби, дижонская горчица, рисовый уксус, масло виноградной косточки, сок лайма, сметана)" }
    ]
  },
  {
    "category": "Закуски",
    "name": "оливки",
    "content": [
      { "label": "оливки зеленые", "full": "оливки зеленые" },
      { "label": "оливки гигант (Испания)", "full": "оливки гигант (Испания)" },
      { "label": "перец", "full": "перец" },
      { "label": "чеснок", "full": "чеснок" },
      { "label": "уксус", "full": "уксус" },
      { "label": "паприка", "full": "паприка" },
      { "label": "орегано", "full": "орегано" }
    ],
    "sauce": []
  },
  {
    "category": "Закуски",
    "name": "картофель фри с пекорино",
    "content": [
      { "label": "картофель фри", "full": "картофель фри" },
      { "label": "тертый пекорино", "full": "тертый пекорино" }
    ],
    "sauce": []
  },
  {
    "category": "Закуски",
    "name": "трюфельный камамбер с салатом и соусом из лукового конфитюра",
    "content": [
      { "label": "трюфельный камамбер", "full": "трюфельный камамбер (камамбер, трюфельный крем: трюфельная паста, трюфельное масло, соевый соус, шампиньоны, креметта)" },
      { "label": "микс салата", "full": "микс салата" }
    ],
    "sauce": [
      { "label": "соус на основе карамелизированного лука", "full": "соус на основе карамелизированного лука (масло олив, соус шисо, фреш лимон, винный уксус, сах. сироп, луковый мармелад)" },
      { "label": "луковый мармелад", "full": "луковый мармелад (лук шалот, мед, уксус, сливочное масло, соль)" }
    ]
  },
  {
    "category": "Бранч",
    "name": "крок-месье с тамбовским окороком, пекорино, трюфелем и маринованным редисом",
    "content": [],
    "sauce": []
  },
  {
    "category": "Бранч",
    "name": "бургер с карамелизированным луком и беконом",
    "content": [],
    "sauce": []
  },
  {
    "category": "К вину",
    "name": "устрица Дибба Бэй",
    "content": [],
    "sauce": [],
    "pairing": ["Отлично подходит к белому вину"]
  },
  {
    "category": "К вину",
    "name": "устрица Муроцу",
    "content": [],
    "sauce": []
  },
  {
    "category": "К вину",
    "name": "устрица Розовая Джоли",
    "content": [],
    "sauce": []
  },
  {
    "category": "К вину",
    "name": "сет устриц: Дибба Бэй, Муроцу, Розовая Джоли",
    "content": [
      { "label": "устрица Дибба Бэй", "full": "устрица Дибба Бэй" },
      { "label": "устрица Муроцу", "full": "устрица Муроцу" },
      { "label": "устрица Розовая Джоли", "full": "устрица Розовая Джоли" }
    ],
    "sauce": [
      { "label": "соевый соус", "full": "соевый соус" },
      { "label": "рисовый уксус", "full": "рисовый уксус" },
      { "label": "фреш апельсин/лайм", "full": "фреш апельсин/лайм" },
      { "label": "мирин", "full": "мирин" },
      { "label": "лук шалот", "full": "лук шалот" },
      { "label": "кинза", "full": "кинза" },
      { "label": "маринованный болгарский перец", "full": "маринованный болгарский перец" }
    ]
  },
  {
    "category": "К вину",
    "name": "морской ёж с желтком конфи, понзу и огурцом",
    "content": [
      { "label": "желток конфи", "full": "желток конфи (желток, красный винный уксус, соль)" },
      { "label": "свежий огурец", "full": "свежий огурец" }
    ],
    "sauce": [
      { "label": "соус понзу", "full": "соус понзу (соевый соус, фреш лимон/апельсин, стружка тунца, водоросли комбу, сахар, цедра лайма)" }
    ]
  },
  {
    "category": "К вину",
    "name": "татаки из тунца с понзу, кремом из авокадо и маринованным фенхелем",
    "content": [
      { "label": "опаленный тунец", "full": "опаленный тунец" },
      { "label": "маринованный фенхель", "full": "маринованный фенхель (уксус, сахар, вода)" },
      { "label": "масло шичими тогараши", "full": "масло шичими тогараши" }
    ],
    "sauce": [
      { "label": "соус понзу", "full": "соус понзу (соевый соус, фреш лимон/апельсин, стружка тунца, водоросли комбу, сахар, цедра лайма)" },
      { "label": "крем авокадо", "full": "крем авокадо (авокадо, сок лайма, рисовый уксус, шпинат, мята)" }
    ]
  },
  {
    "category": "К вину",
    "name": "лосось с имбирным соусом",
    "content": [
      { "label": "свежий лосось", "full": "свежий лосось" },
      { "label": "кунжут кимчи", "full": "кунжут кимчи" }
    ],
    "sauce": [
      { "label": "дрессинг из хрена", "full": "дрессинг из хрена (корень хрена, корень имбиря, соевый соус, рисовый уксус, мёд, масло виноградной косточки)" }
    ]
  },
  {
    "category": "К вину",
    "name": "утка магре с маринованной черешней и соусом из кленового сиропа и фенхеля",
    "content": [
      { "label": "сырокопчёная утиная грудка", "full": "сырокопчёная утиная грудка" },
      { "label": "маринованная черешня", "full": "маринованная черешня (бальзамический уксус, тростниковый сахар, корица, чеснок)" }
    ],
    "sauce": [
      { "label": "кленовый сироп на семенах фенхеля", "full": "кленовый сироп на семенах фенхеля" }
    ]
  },
  {
    "category": "К вину",
    "name": "картофель фри с трюфельным мороженым",
    "content": [
      { "label": "картофель фри", "full": "картофель фри" },
      { "label": "трюфельное мороженое", "full": "трюфельное мороженое (яйцо, сливки, сахар, соль, трюфельная паста, трюфельное масло)" },
      { "label": "слайсы трюфеля", "full": "слайсы трюфеля" }
    ],
    "sauce": []
  },
  {
    "category": "Супы",
    "name": "гаспачо из жёлтых томатов с малиной, страчателлой и соусом из эстрагона",
    "content": [],
    "sauce": []
  },
  {
    "category": "Супы",
    "name": "рыбный суп с палтусом и брокколи",
    "content": [],
    "sauce": []
  },
  {
    "category": "Салаты",
    "name": "острый салат с томатами, печёным перцем, романо и фетой",
    "content": [
      { "label": "томаты", "full": "томаты" },
      { "label": "запеченный перец", "full": "запеченный перец" },
      { "label": "листья салата романо", "full": "листья салата романо" },
      { "label": "киноа", "full": "киноа" },
      { "label": "сыр фета", "full": "сыр фета" },
      { "label": "базилик", "full": "базилик" }
    ],
    "sauce": [
      { "label": "острая заправка", "full": "острая заправка (соус унаги, майонез, свит чили, чеснок, фреш лимон, оливковое масло, халапеньо, шрирача, растительное масло)" }
    ]
  },
  {
    "category": "Салаты",
    "name": "зелёный салат с авокадо",
    "content": [
      { "label": "микс салата", "full": "микс салата" },
      { "label": "авокадо", "full": "авокадо" },
      { "label": "слайсы пекорино", "full": "слайсы пекорино" }
    ],
    "sauce": [
      { "label": "лимонный сок", "full": "лимонный сок" },
      { "label": "оливковое масло", "full": "оливковое масло" },
      { "label": "мед", "full": "мед" },
      { "label": "горчица", "full": "горчица" },
      { "label": "семена чиа", "full": "семена чиа" }
    ]
  },
  {
    "category": "Салаты",
    "name": "салат с томатами, огурцами, сельдереем и страккино",
    "content": [
      { "label": "микс салата", "full": "микс салата" },
      { "label": "томаты", "full": "томаты" },
      { "label": "огурцы", "full": "огурцы" },
      { "label": "редис", "full": "редис" },
      { "label": "сельдерей", "full": "сельдерей" },
      { "label": "мята", "full": "мята" },
      { "label": "сыр стракино", "full": "сыр стракино" }
    ],
    "sauce": [
      { "label": "заправка бостон", "full": "заправка бостон (лимонный сок, оливковое масло, горчица, мед)" }
    ]
  },
  {
    "category": "Салаты",
    "name": "буррата с томатами, маракуйей и печеньем из орегано",
    "content": [
      { "label": "томаты", "full": "томаты" },
      { "label": "свежая маракуйя", "full": "свежая маракуйя" },
      { "label": "целая буррата", "full": "целая буррата" },
      { "label": "орегано кранч", "full": "орегано кранч" },
      { "label": "масло базилик", "full": "масло базилик" }
    ],
    "sauce": [
      { "label": "заправка бостон", "full": "заправка бостон" }
    ]
  },
  {
    "category": "Рыба",
    "name": "тигровые креветки с романо на гриле, айоли из угря и соусом руй",
    "content": [
      { "label": "качан салата романо", "full": "качан салата романо (рассол: вода, сахар, соль)" },
      { "label": "креветки", "full": "креветки" },
      { "label": "чеснок", "full": "чеснок" },
      { "label": "чили", "full": "чили" },
      { "label": "макранч", "full": "макранч" }
    ],
    "sauce": [
      { "label": "соус руй", "full": "соус руй в азиатском стиле (свитчили, яйцо, печеный чеснок, шрирача, кайенский перец, дижонская горчица, растительное масло)" },
      { "label": "копченый айоли", "full": "копченый айоли (домашний майонез, копченое растительное масло, чернила каракатицы)" }
    ]
  },
  {
    "category": "Рыба",
    "name": "камбала с соусом пиль пиль и виноградом",
    "content": [
      { "label": "филе камбалы", "full": "филе камбалы" },
      { "label": "красный виноград", "full": "красный виноград" },
      { "label": "сливочное масло", "full": "сливочное масло" }
    ],
    "sauce": [
      { "label": "соус пиль-пиль", "full": "соус (рыбный бульон, сливочное масло, чеснок, лук шалот, каперсы, вяленые томаты, оливки, петрушка)" }
    ]
  },
  {
    "category": "Рыба",
    "name": "лосось с пюре из карамелизированной моркови и соусом из эстрагона",
    "content": [
      { "label": "половина стейка лосося", "full": "половина стейка лосося" },
      { "label": "печеная морковь", "full": "печеная морковь (сливочное масло, оливковое масло, мед, специи чатни: шичими тогараси, кориандр, черный перец, фенхель, сушеные лук и чеснок)" }
    ],
    "sauce": [
      { "label": "пюре из карамелизированной моркови", "full": "пюре из карамелизированной моркови (карамелизированная морковь, сливочное масло)" },
      { "label": "соус эстрагон", "full": "соус эстрагон (эстрагон, петрушка)" }
    ]
  },
  {
    "category": "Рыба",
    "name": "палтус со сморчками, кремом из белого лука и муссом из белых грибов и водорослей",
    "content": [
      { "label": "половина филе палтуса", "full": "половина филе палтуса" },
      { "label": "обжаренные сморчки", "full": "обжаренные сморчки" }
    ],
    "sauce": [
      { "label": "мусс из белых грибов", "full": "мусс из белых грибов (даси из водорослей и стружки бонито, пророщенные на перловке кодзи, белые грибы, сливки)" },
      { "label": "луковый крем", "full": "луковый крем (карамелизированный лук, сливки, мисо паста, соль, мед)" }
    ]
  },
  {
    "category": "Мясо",
    "name": "перепёлка с грибным муссом и соусом лайм-хойсин",
    "content": [
      { "label": "перепелка", "full": "перепелка (голень и крылья)" },
      { "label": "мусс-начинка", "full": "мусс-начинка из куриного бедра, обжаренного лука и шампиньонов" },
      { "label": "картофель пай", "full": "картофель пай" }
    ],
    "sauce": [
      { "label": "соус хойсин", "full": "соус хойсин (куриный жу: куриный бульон, лук, морковь, имбирь, сок лайма, листья лайма, хойсин)" }
    ]
  },
  {
    "category": "Мясо",
    "name": "утиная ножка с печёной морковью и горгонзолой",
    "content": [
      { "label": "утиная нога", "full": "утиная нога (су-вид со сливочным маслом и соевым соусом)" },
      { "label": "печеная морковь", "full": "печеная морковь (сливочное масло, оливковое масло, мед, специи чатни: шичими тогараси, кориандр, черный перец, фенхель, сушеные лук и чеснок)" },
      { "label": "сыр дорблю", "full": "сыр дорблю" }
    ],
    "sauce": [
      { "label": "соус", "full": "соус (куриный жу: куриный бульон, лук, морковь, имбирь, сок лайма, листья лайма, хойсин)" }
    ]
  },
  {
    "category": "Мясо",
    "name": "говяжий язык с жареным романо, перечным соусом и сметаной",
    "content": [
      { "label": "говяжий язык", "full": "говяжий язык" },
      { "label": "листья романо", "full": "листья романо" },
      { "label": "чили кунжут", "full": "чили кунжут" }
    ],
    "sauce": [
      { "label": "сметана", "full": "сметана" },
      { "label": "перечный соус", "full": "перечный соус (сливочное масло, растительное масло, репчатый лук, чеснок, сахар, томатная паста, ворчестер, сладкий чили, соевый соус, вода)" }
    ]
  },
  {
    "category": "Мясо",
    "name": "говяжья щека с перцем рамиро и картофельным пюре",
    "content": [
      { "label": "говяжьи щечки", "full": "говяжьи щечки (томленые в красном вине с чесноком, тимьяном, луком, шампиньонами и сливочным маслом)" },
      { "label": "перец рамиро", "full": "перец рамиро" },
      { "label": "картофельное пюре", "full": "картофельное пюре" }
    ],
    "sauce": [
      { "label": "соус", "full": "соус (соус лаогама, соус кальби, чеснок, лук, устричный соус, масло растительное)" }
    ]
  },
  {
    "category": "Мясо",
    "name": "говяжья печень с домашним карри",
    "content": [
      { "label": "стейк из печени", "full": "стейк из печени (вымоченный в соленом растворе)" },
      { "label": "обжаренный арахис", "full": "обжаренный арахис" },
      { "label": "кинза", "full": "кинза" }
    ],
    "sauce": [
      { "label": "карри-соус", "full": "карри-соус (лук, чеснок, имбирь, зира, чили, куркума, кардамон, сливочное масло, куриный бульон)" },
      { "label": "демиглас", "full": "демиглас" }
    ]
  },
  {
    "category": "Мясо",
    "name": "коджи-рибай с цветком цукини и фуа-гра",
    "content": [],
    "sauce": []
  },
  {
    "category": "Мясо",
    "name": "бавет с перечным соусом",
    "content": [
      { "label": "стейк бавет", "full": "стейк бавет (маринован в солевом растворе)" },
      { "label": "сибулет", "full": "сибулет" }
    ],
    "sauce": [
      { "label": "перечный соус", "full": "перечный соус (сливки, демиглясс, соль, перец, маринованный черный перец)" }
    ],
    "pairing": "рекомендуем к стейку красное сухое вино, например, Каберне Совиньон"
  },
  {
    "category": "Овощи",
    "name": "брокколи с соусом из васаби",
    "content": [
      { "label": "брокколи", "full": "брокколи" },
      { "label": "специи фурикаке", "full": "специи фурикаке (стружка тунца, кунжут, нори)" },
      { "label": "свежая кинза", "full": "свежая кинза" }
    ],
    "sauce": [
      { "label": "соус васаби", "full": "соус васаби (унаги, васаби, майонез, вода)" },
      { "label": "зеленое масло базилика", "full": "зеленое масло базилика" }
    ]
  },
  {
    "category": "Овощи",
    "name": "перлотто с грибами и копченой грушей",
    "content": [],
    "sauce": []
  },
  {
    "category": "Бранч",
    "name": "спаржа с яйцом пашот и пекорино",
    "content": [],
    "sauce": []
  },
  {
    "category": "Паста",
    "name": "орзо с гребешком и кремом из грибов",
    "content": [
      { "label": "паста орзо", "full": "паста орзо (сливки, сыр пеккорино, сливочное масло)" },
      { "label": "гребешок", "full": "гребешок" },
      { "label": "оливковое масло", "full": "оливковое масло" },
      { "label": "лук сибулет", "full": "лук сибулет" },
      { "label": "пудра из ферментированного шалота", "full": "пудра из ферментированного шалота" }
    ],
    "sauce": [
      { "label": "крем из грибов", "full": "крем из грибов (шампиньоны, соевый соус, трюфельная паста, трюфельное масло)" }
    ]
  },
  {
    "category": "Паста",
    "name": "ризотто качо э пепе с осьминогом",
    "content": [
      { "label": "рис акварелла", "full": "рис акварелла" },
      { "label": "лук шалот", "full": "лук шалот" },
      { "label": "чеснок", "full": "чеснок" },
      { "label": "тимьян", "full": "тимьян" },
      { "label": "черный перец", "full": "черный перец" },
      { "label": "белое вино", "full": "белое вино" },
      { "label": "сливочное масло", "full": "сливочное масло" },
      { "label": "пекорино", "full": "пекорино" },
      { "label": "осьминог отварной", "full": "осьминог отварной (маринад: лук, морковь, имбирь, чеснок, куриный бульон кнорр, соевый соус)" },
      { "label": "оливковое масло", "full": "оливковое масло" }
    ],
    "sauce": []
  },
  {
    "category": "Паста",
    "name": "каламарата с копчёным лососем и маринованным фенхелем",
    "content": [
      { "label": "лосось", "full": "лосось (копчение собственное)" },
      { "label": "фенхель маринованный", "full": "фенхель маринованный (уксус, вода, сахар)" },
      { "label": "паста каламарата", "full": "паста каламарата" },
      { "label": "пыль вакаме", "full": "пыль вакаме" },
      { "label": "фурикаке", "full": "фурикаке" }
    ],
    "sauce": [
      { "label": "соус на белом вине со сливками", "full": "соус на белом сухом вине со сливками (лук шалот)" }
    ]
  },
  {
    "category": "Паста",
    "name": "казаречче с утиной ножкой конфи и муссом из пекорино",
    "content": [
      { "label": "паста казаречче", "full": "паста казаречче" },
      { "label": "утиная ножка конфи", "full": "утиная ножка конфи (красное вино, карамелизированный лук, демигляс, сливочное масло)" },
      { "label": "зеленый лук", "full": "зеленый лук" }
    ],
    "sauce": [
      { "label": "мусс пекорино", "full": "мусс пекорино (кремета, сливки, пекорино)" }
    ]
  },
  {
    "category": "Бранч",
    "name": "паппарделле с лисичками",
    "content": [],
    "sauce": []
  },
  {
    "category": "Десерты",
    "name": "арбуз, дыня, черешня, клубника",
    "content": [],
    "sauce": []
  },
  {
    "category": "Десерты",
    "name": "глазированная слива с мороженым Педро Хименес",
    "content": [
      { "label": "слива", "full": "слива (карамелизированная в сахаре)" },
      { "label": "сливочное масло", "full": "сливочное масло" },
      { "label": "орегано кранч", "full": "орегано кранч" },
      { "label": "мороженое с хересом Педро Хименес", "full": "мороженое с хересом Педро Хименес" }
    ],
    "sauce": [
      { "label": "винный сироп с ванилью", "full": "винный сироп с ванилью" }
    ]
  },
  {
    "category": "Десерты",
    "name": "панна-котта из гречишного мёда с сорбетом из дыни и ягодным компоте",
    "content": [
      { "label": "панна-котта", "full": "панна-котта (сливки, желатин говяжий, гречишный мед)" },
      { "label": "кнель дынного сорбета", "full": "кнель дынного сорбета" },
      { "label": "меренга", "full": "меренга (с добавлением винного уксуса)" }
    ],
    "sauce": [
      { "label": "ягодное компоте", "full": "компоте из клубники, голубики и малины (лимонный сок, сахар, сублимированная малина)" }
    ]
  },
  {
    "category": "Десерты",
    "name": "чизкейк с кленовым сиропом",
    "content": [
      { "label": "сыр креметта", "full": "сыр креметта" },
      { "label": "сливки", "full": "сливки" },
      { "label": "яйца", "full": "яйца" },
      { "label": "кукурузный крахмал", "full": "кукурузный крахмал" },
      { "label": "сахар", "full": "сахар" }
    ],
    "sauce": [
      { "label": "крем сверху", "full": "крем сверху (креметта, молоко, желатин, сахар)" },
      { "label": "кленовый сироп", "full": "кленовый сироп" }
    ]
  },
  {
    "category": "Десерты",
    "name": "медовые пышки с мороженым и грецким орехом",
    "content": [
      { "label": "тесто пончиковое", "full": "тесто пончиковое (мука пшеничная, картофель, дрожжи, молоко, яйцо куриное, соль, мед, сливочное масло)" },
      { "label": "сахар", "full": "сахар" },
      { "label": "корица молотая", "full": "корица молотая" },
      { "label": "пломбир", "full": "пломбир (яйцо, сливки, сахар, соль)" },
      { "label": "грецкий орех карамелизированный", "full": "грецкий орех карамелизированный" }
    ],
    "sauce": [
      { "label": "медовый сироп", "full": "медовый сироп" }
    ]
  },
  {
    "category": "Десерты",
    "name": "шоколадная конфета 1 шт. / 3 шт.",
    "content": [
      { "label": "шоколад горький 30%", "full": "шоколад горький 30%" },
      { "label": "шоколад молочный 70%", "full": "шоколад молочный 70%" },
      { "label": "творожный сыр креметта", "full": "творожный сыр креметта" },
      { "label": "какао", "full": "какао" },
      { "label": "орегано начинка", "full": "орегано-начинка (орехи грецкие, мука, орегано, сливочное масло, соль, сахар)" }
    ],
    "sauce": []
  },
  {
    "category": "Десерты",
    "name": "мороженое",
    "content": [
      { "label": "сливки", "full": "сливки" },
      { "label": "желток", "full": "желток" },
      { "label": "сахар", "full": "сахар" }
    ],
    "sauce": []
  },
  {
    "category": "Бранч",
    "name": "манная каша с ягодным компоте и печеньем с орегано",
    "content": [],
    "sauce": []
  },
  {
    "category": "Бранч",
    "name": "жареная колбаса с яйцом, горошком и тартином",
    "content": [],
    "sauce": []
  },
  {
    "category": "Бранч",
    "name": "турецкая яичница с перцем конфи",
    "content": [],
    "sauce": []
  },
  {
    "category": "Бранч",
    "name": "скрембл со шпинатом в белом вине",
    "content": [],
    "sauce": []
  },
  {
    "category": "Бранч",
    "name": "пшённая каша с беконом и муссом из пекорино",
    "content": [],
    "sauce": []
  },
  {
    "category": "Добавки к бранчу",
    "name": "лосось (30 г)",
    "content": [],
    "sauce": []
  },
  {
    "category": "Добавки к бранчу",
    "name": "бекон (40 г)",
    "content": [],
    "sauce": []
  },
  {
    "category": "Добавки к бранчу",
    "name": "перец конфи (50 г)",
    "content": [],
    "sauce": []
  },
  {
    "category": "Добавки к бранчу",
    "name": "авокадо (50 г)",
    "content": [],
    "sauce": []
  },
  {
    "category": "Ночное меню",
    "name": "устрица Дибба Бэй",
    "content": [],
    "sauce": []
  },
  {
    "category": "Ночное меню",
    "name": "устрица Муроцу",
    "content": [],
    "sauce": []
  },
  {
    "category": "Ночное меню",
    "name": "устрица Розовая Джоли",
    "content": [],
    "sauce": []
  },
  {
    "category": "Ночное меню",
    "name": "сет устриц: Дибба Бэй, Муроцу, Розовая Джоли",
    "content": [
      { "label": "устрица Дибба Бэй", "full": "устрица Дибба Бэй" },
      { "label": "устрица Муроцу", "full": "устрица Муроцу" },
      { "label": "устрица Розовая Джоли", "full": "устрица Розовая Джоли" }
    ],
    "sauce": [
      { "label": "соевый соус", "full": "соевый соус" },
      { "label": "рисовый уксус", "full": "рисовый уксус" },
      { "label": "фреш апельсин/лайм", "full": "фреш апельсин/лайм" },
      { "label": "мирин", "full": "мирин" },
      { "label": "лук шалот", "full": "лук шалот" },
      { "label": "кинза", "full": "кинза" },
      { "label": "маринованный болгарский перец", "full": "маринованный болгарский перец" }
    ]
  },
  {
    "category": "Ночное меню",
    "name": "морской ёж с желтком конфи, понзу и огурцом",
    "content": [
      { "label": "желток конфи", "full": "желток конфи (желток, красный винный уксус, соль)" },
      { "label": "свежий огурец", "full": "свежий огурец" }
    ],
    "sauce": [
      { "label": "соус понзу", "full": "соус понзу (соевый соус, фреш лимон/апельсин, стружка тунца, водоросли комбу, сахар, цедра лайма)" }
    ]
  },
  {
    "category": "Ночное меню",
    "name": "паштет из куриной печени с чёрной смородиной",
    "content": [
      { "label": "печень", "full": "печень" },
      { "label": "бульон куриный", "full": "бульон куриный" },
      { "label": "вино красное", "full": "вино красное" },
      { "label": "перец", "full": "перец" },
      { "label": "соль", "full": "соль" },
      { "label": "масло сливочное", "full": "масло сливочное" },
      { "label": "яйцо куриное", "full": "яйцо куриное" },
      { "label": "чеснок", "full": "чеснок" },
      { "label": "лук белый", "full": "лук белый" },
      { "label": "коньяк армянский", "full": "коньяк армянский" },
      { "label": "бриошь", "full": "бриошь" },
      { "label": "кранч орегано", "full": "кранч орегано (грецкий орех, мука пшеничная, сливочное и оливковое масло, орегано сухой, сахар, соль)" }
    ],
    "sauce": [
      { "label": "варенье из черной смородины с мятой", "full": "варенье из черной смородины с мятой" }
    ]
  },
  {
    "category": "Ночное меню",
    "name": "тартар из говядины с вяленой свеклой, пекорино и картофелем фри",
    "content": [
      { "label": "говядина зернового откорма", "full": "говядина зернового откорма (бавет — вырезка из нижней части живота)" },
      { "label": "вяленая свекла", "full": "вяленая свекла" },
      { "label": "тертый пекорино", "full": "тертый пекорино" },
      { "label": "картофель фри или бриошь", "full": "картофель фри или бриошь" }
    ],
    "sauce": [
      { "label": "каперсы", "full": "каперсы" },
      { "label": "лимонный сок", "full": "лимонный сок" },
      { "label": "соус для свеклы", "full": "соус для восстановления свеклы (вустершир, горчица, шрирача, оливковое масло)" }
    ]
  },
  {
    "category": "Ночное меню",
    "name": "холодец из утиной ножки с кремом из васаби и бородинским хлебом",
    "content": [
      { "label": "бульон на холодец", "full": "бульон на холодец (утка, курица, соевый соус, бадьян, корица)" },
      { "label": "бородинский хлеб", "full": "бородинский хлеб" },
      { "label": "битый огурец", "full": "битый огурец (маринад из соуса кимчи, соков апельсина и лайма, соевого соуса)" },
      { "label": "васаби кидзами", "full": "васаби кидзами (мелко нарезанный стебель)" }
    ],
    "sauce": [
      { "label": "васаби крем", "full": "васаби крем (белок, паста васаби, дижонская горчица, рисовый уксус, масло виноградной косточки, сок лайма, сметана)" }
    ]
  },
  {
    "category": "Ночное меню",
    "name": "картофельные пышки со сметаной и щучьей икрой",
    "content": [
      { "label": "тесто пончиковое", "full": "тесто пончиковое (мука пшеничная, картофель, дрожжи, молоко, яйцо куриное, соль, сливочное масло)" },
      { "label": "щучья икра", "full": "щучья икра" },
      { "label": "лук сибулет", "full": "лук сибулет" },
      { "label": "пыль из шалота", "full": "пыль из шалота" }
    ],
    "sauce": [
      { "label": "сметана копченая", "full": "сметана копченая" }
    ]
  },
  {
    "category": "Ночное меню",
    "name": "картофель фри с пекорино",
    "content": [
      { "label": "картофель фри", "full": "картофель фри" },
      { "label": "тертый пекорино", "full": "тертый пекорино" }
    ],
    "sauce": []
  },
  {
    "category": "Ночное меню",
    "name": "брокколи с соусом из васаби",
    "content": [
      { "label": "брокколи", "full": "брокколи" },
      { "label": "специи фурикаке", "full": "специи фурикаке (стружка тунца, кунжут, нори)" },
      { "label": "свежая кинза", "full": "свежая кинза" }
    ],
    "sauce": [
      { "label": "соус васаби", "full": "соус васаби (унаги, васаби, майонез, вода)" },
      { "label": "зеленое масло базилика", "full": "зеленое масло базилика" }
    ]
  },
  {
    "category": "Ночное меню",
    "name": "бавет с перечным соусом",
    "content": [
      { "label": "стейк бавет", "full": "стейк бавет (маринован в солевом растворе)" },
      { "label": "сибулет", "full": "сибулет" }
    ],
    "sauce": [
      { "label": "перечный соус", "full": "перечный соус (сливки, демиглясс, соль, перец, маринованный черный перец)" }
    ]
  },
  {
    "category": "Ночное меню",
    "name": "медовые пышки с мороженым и грецким орехом",
    "content": [
      { "label": "тесто пончиковое", "full": "тесто пончиковое (мука пшеничная, картофель, дрожжи, молоко, яйцо куриное, соль, мед, сливочное масло)" },
      { "label": "сахар", "full": "сахар" },
      { "label": "корица молотая", "full": "корица молотая" },
      { "label": "пломбир", "full": "пломбир (яйцо, сливки, сахар, соль)" },
      { "label": "грецкий орех карамелизированный", "full": "грецкий орех карамелизированный" }
    ],
    "sauce": [
      { "label": "медовый сироп", "full": "медовый сироп" }
    ]
  }
]